timesat-4.2.1.dist-info/LICENSE
timesat-4.2.1.dist-info/WHEEL
timesat-4.2.1.dist-info/METADATA
timesat-4.2.1.dist-info/RECORD
timesat.libs/libquadmath-96973f99.so.0.0.0
timesat.libs/libgomp-a34b3233.so.1.0.0
timesat.libs/libgfortran-040039e1.so.5.0.0
timesat/_timesat.cpython-312-x86_64-linux-gnu.so
timesat/__init__.py
timesat-4.2.1.data/data/timesat/LICENSE
timesat-4.2.1.data/data/timesat/README.md
