Metadata-Version: 2.1
Name: timesat
Version: 4.2.1
Summary: Python bindings to the TIMESAT Fortran core for analyzing satellite time-series data
Keywords: TIMESAT,remote sensing,phenology,time series analysis
Author: Lars Eklundh, Per Jönsson
Author-Email: Zhanzhang Cai <zhanzhang.cai@nateko.lu.se>
License: SPDX-License-Identifier: LicenseRef-Proprietary-TIMESAT-Research-Only
Classifier: Development Status :: 5 - Production/Stable
Classifier: Intended Audience :: Science/Research
Classifier: Topic :: Scientific/Engineering
Classifier: Programming Language :: Python :: 3
Classifier: Programming Language :: Python :: 3 :: Only
Classifier: Programming Language :: Python :: 3.10
Classifier: Programming Language :: Python :: 3.11
Classifier: Programming Language :: Python :: 3.12
Classifier: Programming Language :: Fortran
Classifier: Operating System :: MacOS
Classifier: Operating System :: POSIX :: Linux
Classifier: Operating System :: Microsoft :: Windows
Classifier: License :: Other/Proprietary License
Project-URL: Homepage, https://github.com/TIMESAT
Project-URL: ORCID, https://orcid.org/0000-0001-5883-4575
Requires-Python: >=3.10
Requires-Dist: numpy>=2.0
